simdec/__init__.py
simdec/auth.py
simdec/decomposition.py
simdec/sensitivity_indices.py
simdec/visualization.py
simdec-1.5.0.dist-info/METADATA
simdec-1.5.0.dist-info/WHEEL
simdec-1.5.0.dist-info/entry_points.txt
simdec-1.5.0.dist-info/licenses/LICENSE.txt
simdec-1.5.0.dist-info/RECORD
