Metadata-Version: 2.4
Name: simdec
Version: 1.5.0
Summary: Sensitivity analysis using simulation decomposition
Project-URL: homepage, https://www.simdec.fi/
Project-URL: documentation, https://simdec.readthedocs.io
Project-URL: source, https://github.com/Simulation-Decomposition/simdec-python
Author: Pamphile Roy
Maintainer: simdec contributors
License-Expression: BSD-3-Clause
License-File: LICENSE.txt
Classifier: Intended Audience :: Developers
Classifier: Intended Audience :: End Users/Desktop
Classifier: Intended Audience :: Science/Research
Classifier: License :: OSI Approved :: BSD License
Classifier: Operating System :: OS Independent
Classifier: Programming Language :: Python
Classifier: Programming Language :: Python :: 3
Classifier: Programming Language :: Python :: 3.11
Classifier: Programming Language :: Python :: 3.12
Classifier: Programming Language :: Python :: 3.13
Requires-Python: >=3.11
Requires-Dist: numpy
Requires-Dist: pandas
Requires-Dist: salib
Requires-Dist: seaborn
Provides-Extra: dashboard
Requires-Dist: cryptography; extra == 'dashboard'
Requires-Dist: panel>=1.4.5; extra == 'dashboard'
Provides-Extra: dev
Requires-Dist: accessible-pygments; extra == 'dev'
Requires-Dist: cryptography; extra == 'dev'
Requires-Dist: hatch; extra == 'dev'
Requires-Dist: myst-nb; extra == 'dev'
Requires-Dist: numpydoc; extra == 'dev'
Requires-Dist: panel>=1.4.5; extra == 'dev'
Requires-Dist: pre-commit; extra == 'dev'
Requires-Dist: pydata-sphinx-theme; extra == 'dev'
Requires-Dist: pytest; extra == 'dev'
Requires-Dist: pytest-cov; extra == 'dev'
Requires-Dist: sphinx; extra == 'dev'
Requires-Dist: watchfiles; extra == 'dev'
Provides-Extra: doc
Requires-Dist: accessible-pygments; extra == 'doc'
Requires-Dist: myst-nb; extra == 'doc'
Requires-Dist: numpydoc; extra == 'doc'
Requires-Dist: pydata-sphinx-theme; extra == 'doc'
Requires-Dist: sphinx; extra == 'doc'
Provides-Extra: test
Requires-Dist: pytest; extra == 'test'
Requires-Dist: pytest-cov; extra == 'test'
